lias.py
lias-0.3.0.dist-info/METADATA
lias-0.3.0.dist-info/RECORD
lias-0.3.0.dist-info/WHEEL
lias-0.3.0.dist-info/entry_points.txt
lias-0.3.0.dist-info/top_level.txt
